MANIFEST.in
README.md
VERSION
requirements.txt
setup.py
docs/source/conf.py
unimatrix.ext.model.egg-info/PKG-INFO
unimatrix.ext.model.egg-info/SOURCES.txt
unimatrix.ext.model.egg-info/dependency_links.txt
unimatrix.ext.model.egg-info/requires.txt
unimatrix.ext.model.egg-info/top_level.txt
unimatrix/ext/model/__init__.py
unimatrix/ext/model/entity.py
unimatrix/ext/model/factory.py
unimatrix/ext/model/package.json
unimatrix/ext/model/repository.py
unimatrix/ext/model/exc/__init__.py
unimatrix/ext/model/exc/base.py
unimatrix/ext/model/exc/pydantic.py
unimatrix/ext/model/exc/schema/__init__.py
unimatrix/ext/model/exc/schema/base.py
unimatrix/ext/model/exc/schema/canonical.py
unimatrix/ext/model/exc/schema/validationerror.py
unimatrix/ext/model/exc/tests/__init__.py
unimatrix/ext/model/exc/tests/test_unit_collectionvalidationerror.py
unimatrix/ext/model/exc/tests/test_unit_logging.py
unimatrix/ext/model/exc/tests/test_unit_pydantic_schema.py
unimatrix/ext/model/exc/tests/test_unit_validationerror.py
unimatrix/ext/model/tests/__init__.py
unimatrix/ext/model/tests/test_unit_repository_creation.py